{
    "pacman": [
        "linux-headers",
        "pavucontrol",
        "lxappearance",
        "git",
        "git-lfs",
        "lazygit",
        "cmake",
        "ccls",
        "fish",
        "alacritty",
        "vim",
        "neovim",
        "nano",
        "helix",
        "npm",
        "nodejs",
        "tmux",
        "python",
        "exa",
        "bat",
        "ripgrep",
        "fd",
        "feh",
        "neofetch",
        "maim",
        "ranger",
        "screenkey",
        "stow",
        "curl",
        "xclip",
        "man",
        "zip", "unzip",
        "min",
        "firefox",
        "vivaldi",
        "vlc",
        "obs-studio",
        "xpdf",
        "libreoffice",
        "obsidian",
        "udiskie",
        "udisks2",
        "telegram-desktop",
        "discord",
        "mono",
        "mono-msbuild",
        "mono-tools",
        "dotnet-runtime",
        "dotnet-sdk",
        "gphoto2",
        "qbittorrent",
        "editorconfig-checker",
        "editorconfig-core-c",
        "thunar",
        "openvpn",
        "openssh",
        "v4l2loopback-dkms",
        "v4l2loopback-utils",
        "gimp",
        "i3-gaps",
        "i3status",
        "i3lock",
        "i3blocks",
        "dmenu",
        "xorg-xinput",
        "xorg-xinit",
        "brightnessctl",
        "emacs",
        "noto-fonts",
        "noto-fonts-emoji",
        "noto-fonts-extra",
        "noto-fonts-cjk",
        "steam",
        "bitwarden",
        "pass",
        "picom",
        "thefuck",
        "papirus-icon-theme",
        "rofi",
        "polybar",
        "tk"
    ],
    "pip": [
        "virtualfish",
        "scons",
        "jedi",
        "jedi-language-server",
        "pynvim",
        "ueberzug"
    ],
    "npm": [
        "neovim",
        "git-open"
    ],
    "omf": [
        "nai"
    ],
    "stow": [
        "xorg",
        "i3",
        "i3exit",
        "i3status",
        "picom",
        "git",
        "lazygit", 
        "nvim",
        "tmux",
        "fish",
        "alacritty",
        "screenkey",
        "ranger"
    ]
}
